README.md
setup.py
pieplinepy.egg-info/PKG-INFO
pieplinepy.egg-info/SOURCES.txt
pieplinepy.egg-info/dependency_links.txt
pieplinepy.egg-info/top_level.txt
pipelinepy/__init__.py
pipelinepy/pipeline.py
pipelinepy/transformations.py
pipelinepy/utilities.py