Metadata-Version: 2.1
Name: pieplinepy
Version: 0.2
Summary: A custom pipeline library for data transformations
Home-page: https://github.com/mzakariabigdata/pieplinepy
Author: Zakaria Morchid
Author-email: morchid.zakariaa@gmail.com
Keywords: pipeline data transformation
Classifier: Development Status :: 3 - Alpha
Classifier: Intended Audience :: Developers
Classifier: Topic :: Software Development :: Libraries :: Python Modules
Classifier: License :: OSI Approved :: MIT License
Classifier: Programming Language :: Python :: 3
Classifier: Programming Language :: Python :: 3.7
Classifier: Programming Language :: Python :: 3.8
Requires-Python: >=3.6
